MANIFEST.in
README.md
requirements.txt
setup.py
mlops_validators/__init__.py
mlops_validators.egg-info/PKG-INFO
mlops_validators.egg-info/SOURCES.txt
mlops_validators.egg-info/dependency_links.txt
mlops_validators.egg-info/requires.txt
mlops_validators.egg-info/top_level.txt
mlops_validators/metrics/__init__.py
mlops_validators/metrics/pandastwodistmetrics.py
mlops_validators/metrics/sparkfeaturechi2goodnessoffitnesstest.py
mlops_validators/metrics/sparkfeatureinformationvalue.py
mlops_validators/metrics/sparkfeaturekolmogorovsmirnovstatistic.py
mlops_validators/metrics/sparkfeaturekullbackleiblerdivergence.py
mlops_validators/metrics/sparkfeaturepopulationstabilityindex.py
mlops_validators/metrics/sparktargetkolmogorovsmirnovstatistic.py
mlops_validators/metrics/sparktargetproportiontest.py
mlops_validators/metrics/sparktwodistmetrics.py
mlops_validators/metrics/twodistmetrics.py
mlops_validators/profiles/__init__.py
mlops_validators/profiles/sparkdatasetmetricprofile.py
mlops_validators/profiles/sparkfeaturemetricprofile.py
mlops_validators/tables/__init__.py
mlops_validators/tables/sparktrainvalidationtable.py
mlops_validators/tables/sparkvalidationtable.py