Metadata-Version: 2.1
Name: mlops-validators
Version: 0.9.5
Summary: An engine to validate Machine Learning models.
Home-page: UNKNOWN
Author: Charles Gobber
Author-email: charles26f@gmail.com
License: Apache-2.0
Platform: UNKNOWN
